phzipcodes/__init__.py
phzipcodes/data/ph_zip_codes.json
phzipcodes/phzipcodes.py
phzipcodes/scraper.py
phzipcodes-0.1.8.dist-info/LICENSE
phzipcodes-0.1.8.dist-info/METADATA
phzipcodes-0.1.8.dist-info/WHEEL
phzipcodes-0.1.8.dist-info/entry_points.txt
phzipcodes-0.1.8.dist-info/RECORD
