Metadata-Version: 2.3
Name: phzipcodes
Version: 0.1.8
Summary: A Python package for Philippines zip codes
License: MIT
Keywords: philippines,zipcode,zipcodes,postal code
Author: Jayson
Author-email: jsoncp@proton.me
Requires-Python: >=3.9,<4.0
Classifier: License :: OSI Approved :: MIT License
Classifier: Programming Language :: Python :: 3
Classifier: Programming Language :: Python :: 3.9
Classifier: Programming Language :: Python :: 3.10
Classifier: Programming Language :: Python :: 3.11
Classifier: Programming Language :: Python :: 3.12
Classifier: Programming Language :: Python :: 3.13
Requires-Dist: aiohttp (>=3.10.10,<4.0.0)
Requires-Dist: bs4 (>=0.0.2,<0.0.3)
Requires-Dist: cachetools (>=5.5.0,<6.0.0)
Requires-Dist: pydantic (>=2.9.2,<3.0.0)
Requires-Dist: toolz (>=1.0.0,<2.0.0)
Project-URL: Repository, https://github.com/jayson-panganiban/phzipcodes
